{
  "build": "h516909a_3",
  "build_number": 3,
  "channel": "https://conda.anaconda.org/bioconda/linux-64",
  "constrains": [],
  "depends": [
    "libgcc-ng >=7.5.0"
  ],
  "extracted_package_dir": "/home/devel/jgomez/.conda/pkgs/aragorn-1.2.38-h516909a_3",
  "features": "",
  "files": [
    "bin/aragorn"
  ],
  "fn": "aragorn-1.2.38-h516909a_3.tar.bz2",
  "license": "GPLv3",
  "link": {
    "source": "/home/devel/jgomez/.conda/pkgs/aragorn-1.2.38-h516909a_3",
    "type": 1
  },
  "md5": "b94e7b6f77485c94b4aec1419d0f4529",
  "name": "aragorn",
  "package_tarball_full_path": "/home/devel/jgomez/.conda/pkgs/aragorn-1.2.38-h516909a_3.tar.bz2",
  "paths_data": {
    "paths": [
      {
        "_path": "bin/aragorn",
        "path_type": "hardlink",
        "sha256": "919906b6f7f6810daf99991ce7d480ba8038a9d90f4dedb62aaf65315b34bdec",
        "sha256_in_prefix": "919906b6f7f6810daf99991ce7d480ba8038a9d90f4dedb62aaf65315b34bdec",
        "size_in_bytes": 466288
      }
    ],
    "paths_version": 1
  },
  "requested_spec": "None",
  "sha256": "163c2e87c96295302f31d72b00eeba3a97df48d3897ecfd17605a23112a012fe",
  "size": 142155,
  "subdir": "linux-64",
  "timestamp": 1594601124763,
  "track_features": "",
  "url": "https://conda.anaconda.org/bioconda/linux-64/aragorn-1.2.38-h516909a_3.tar.bz2",
  "version": "1.2.38"
}